[
  {
    "id": 1,
    "name_la": "1GB (2ມື້)",
    "name_en": "Internet 1GB (2days)",
    "desc_la": "1GB ໃຊ້ໄດ້ 2ມື້",
    "desc_en": "1GB valid for 2days",
    "price": "5000",
    "code": "*559*6#",
    "prereq_la": "",
    "prereq_en": "",
    "category": ["mphone", "net-sim"],
    "steps": ["Dial *559*6#", "Press call", "Wait for confirmation SMS"]
  },
  {
    "id": 2,
    "name_la": "3GB (7ມື້)",
    "name_en": "Internet 3GB (7days)",
    "desc_la": "3GB ໃຊ້ໄດ້ 7ມື້",
    "desc_en": "3GB valid for 7days",
    "price": "10000",
    "code": "*559*7#",
    "prereq_la": "",
    "prereq_en": "",
    "category": ["mphone", "net-sim"],
    "steps": ["Dial *559*7#", "Press call", "Wait for confirmation SMS"]
  },
  {
    "id": 3,
    "name_la": "20GB (30ມື້)",
    "name_en": "Internet 20GB (30days)",
    "desc_la": "20GB ເປັນເວລາ 30ມື້",
    "desc_en": "20GB valid for 30days",
    "price": "60000",
    "code": "*559*8#",
    "prereq_la": "",
    "prereq_en": "",
    "category": ["mphone", "net-sim"],
    "steps": ["Dial *559*8#", "Press call", "Wait for confirmation SMS"]
  },
  {
    "id": 4,
    "name_la": "55GB (30ມື້)",
    "name_en": "Internet 55GB (30days)",
    "desc_la": "55GB ເປັນເວລາ 30ມື້",
    "desc_en": "55GB valid for 30days",
    "price": "120000",
    "code": "*559*9#",
    "prereq_la": "",
    "prereq_en": "",
    "category": ["mphone", "net-sim"],
    "steps": ["Dial *559*9#", "Press call", "Wait for confirmation SMS"]
  },
  {
    "id": 5,
    "name_la": "4.5GB (3ມື້)",
    "name_en": "Internet 4.5GB (3days)",
    "desc_la": "ເບີຕັ້ງໂຕະ",
    "desc_en": "M-Phone",
    "price": "10000",
    "code": "*118*57#",
    "prereq_la": "",
    "prereq_en": "",
    "category": "mphone",
    "steps": ["Dial *118*57#", "Press call", "Wait for confirmation SMS"]
  },
  {
    "id": 6,
    "name_la": "25GB (30ມື້)",
    "name_en": "Internet 25GB (30days)",
    "desc_la": "ເບີຕັ້ງໂຕະ",
    "desc_en": "M-Phone",
    "price": "65000",
    "code": "*118*565#",
    "prereq_la": "",
    "prereq_en": "",
    "category": "mphone",
    "steps": ["Dial *118*565#", "Press call", "Wait for confirmation SMS"]
  },
  {
    "id": 7,
    "name_la": "45GB (30ມື້)",
    "name_en": "Internet 45GB (30days)",
    "desc_la": "ເບີຕັ້ງໂຕະ",
    "desc_en": "M-Phone",
    "price": "100000",
    "code": "*118*567#",
    "prereq_la": "",
    "prereq_en": "",
    "category": "mphone",
    "steps": ["Dial *118*567#", "Press call", "Wait for confirmation SMS"]
  },
  {
    "id": 8,
    "name_la": "70GB (30ມື້)",
    "name_en": "Internet 70GB (30days)",
    "desc_la": "ເບີຕັ້ງໂຕະ",
    "desc_en": "M-Phone",
    "price": "150000",
    "code": "*118*568#",
    "prereq_la": "",
    "prereq_en": "",
    "category": "mphone",
    "steps": ["Dial *118*568#", "Press call", "Wait for confirmation SMS"]
  },
  {
    "id": 9,
    "name_la": "95GB (30ມື້)",
    "name_en": "Internet 95GB (30days)",
    "desc_la": "ເບີຕັ້ງໂຕະ",
    "desc_en": "M-Phone",
    "price": "200000",
    "code": "*118*569#",
    "prereq_la": "",
    "prereq_en": "",
    "category": "mphone",
    "steps": ["Dial *118*569#", "Press call", "Wait for confirmation SMS"]
  },
  {
    "id": 10,
    "name_la": "10GB (10ມື້)",
    "name_en": "10GB (10days)",
    "desc_la": "10GB ໃຊ້ໄດ້ 10ມື້",
    "desc_en": "10GB valid for 10days",
    "price": "25000",
    "code": "*559*1#",
    "prereq_la": "",
    "prereq_en": "",
    "category": ["mphone", "net-sim", "gsm"],
    "steps": ["Dial *559*1#", "Press call", "Wait for confirmation SMS"]
  },
  {
    "id": 11,
    "name_la": "15GB (30ມື້)",
    "name_en": "15GB (30days)",
    "desc_la": "15GB ໃຊ້ໄດ້ 30ມື້",
    "desc_en": "15GB valid for 30days",
    "price": "40000",
    "code": "*559*2#",
    "prereq_la": "",
    "prereq_en": "",
    "category": ["mphone", "net-sim", "gsm"],
    "steps": ["Dial *559*2#", "Press call", "Wait for confirmation SMS"]
  },
  {
    "id": 12,
    "name_la": "35GB (30ມື້)",
    "name_en": "35GB (30days)",
    "desc_la": "35GB ໃຊ້ໄດ້ 30ມື້",
    "desc_en": "35GB valid for 30days",
    "price": "85000",
    "code": "*559*3#",
    "prereq_la": "",
    "prereq_en": "",
    "category": ["mphone", "net-sim", "gsm"],
    "steps": ["Dial *559*3#", "Press call", "Wait for confirmation SMS"]
  },
  {
    "id": 13,
    "name_la": "ແພັກເກັດພິເສດ 3GB (5ມື້)",
    "name_en": "Social Package 3GB (5days)",
    "desc_la": "ແພັກເກັດພິເສດແບບບໍ່ມີຈຳກັດສຳລັບ Facebook, Instagram, Whatsapp, Youtube, Tiktok...",
    "desc_en": "special package unlimited for Facebook, Instagram, Whatsapp, Youtube, Tiktok...",
    "price": "20000",
    "code": "*558*515#",
    "prereq_la": "",
    "prereq_en": "",
    "category": ["mphone", "net-sim", "gsm"],
    "steps": ["Dial *558*515#", "Press call", "Wait for confirmation SMS"]
  },
  {
    "id": 14,
    "name_la": "ແພັກເກັດພິເສດ 10GB (10ມື້)",
    "name_en": "Social Package 10GB (10days)",
    "desc_la": "ແພັກເກັດພິເສດແບບບໍ່ມີຈຳກັດສຳລັບ Facebook, Instagram, Whatsapp, Youtube, Tiktok...",
    "desc_en": "special package unlimited for Facebook, Instagram, Whatsapp, Youtube, Tiktok...",
    "price": "35000",
    "code": "*558*516#",
    "prereq_la": "",
    "prereq_en": "",
    "category": ["mphone", "net-sim", "gsm"],
    "steps": ["Dial *558*516#", "Press call", "Wait for confirmation SMS"]
  },
  {
    "id": 15,
    "name_la": "ແພັກເກັດພິເສດ 15GB (20ມື້)",
    "name_en": "Social Package 15GB (20days)",
    "desc_la": "ແພັກເກັດພິເສດແບບບໍ່ມີຈຳກັດສຳລັບ Facebook, Instagram, Whatsapp, Youtube, Tiktok...",
    "desc_en": "special package unlimited for Facebook, Instagram, Whatsapp, Youtube, Tiktok...",
    "price": "65000",
    "code": "*558*517#",
    "prereq_la": "",
    "prereq_en": "",
    "category": ["mphone", "net-sim", "gsm"],
    "steps": ["Dial *558*517#", "Press call", "Wait for confirmation SMS"]
  },
  {
    "id": 16,
    "name_la": "ແພັກເກັດພິເສດ 30GB (30ມື້)",
    "name_en": "Social Package 30GB (30days)",
    "desc_la": "ແພັກເກັດພິເສດແບບບໍ່ມີຈຳກັດສຳລັບ Facebook, Instagram, Whatsapp, Youtube, Tiktok...",
    "desc_en": "special package unlimited for Facebook, Instagram, Whatsapp, Youtube, Tiktok...",
    "price": "120000",
    "code": "*558*518#",
    "prereq_la": "",
    "prereq_en": "",
    "category": ["mphone", "net-sim", "gsm"],
    "steps": ["Dial *558*518#", "Press call", "Wait for confirmation SMS"]
  },
  {
    "id": 17,
    "name_la": "4.5GB (3ມື້)",
    "name_en": "Internet 4.5GB (3days)",
    "desc_la": "ເບີເນັດ",
    "desc_en": "Net-Sim",
    "price": "10000",
    "code": "*131*57#",
    "prereq_la": "",
    "prereq_en": "",
    "category": "net-sim",
    "steps": ["Dial *131*57#", "Press call", "Wait for confirmation SMS"]
  },
  {
    "id": 18,
    "name_la": "25GB (30ມື້)",
    "name_en": "Internet 25GB (30days)",
    "desc_la": "ເບີເນັດ",
    "desc_en": "Net-Sim",
    "price": "65000",
    "code": "*131*565#",
    "prereq_la": "",
    "prereq_en": "",
    "category": "net-sim",
    "steps": ["Dial *131*565#", "Press call", "Wait for confirmation SMS"]
  },
  {
    "id": 19,
    "name_la": "45GB (30ມື້)",
    "name_en": "Internet 45GB (30days)",
    "desc_la": "ເບີເນັດ",
    "desc_en": "Net-Sim",
    "price": "100000",
    "code": "*131*567#",
    "prereq_la": "",
    "prereq_en": "",
    "category": "net-sim",
    "steps": ["Dial *131*567#", "Press call", "Wait for confirmation SMS"]
  },
  {
    "id": 20,
    "name_la": "70GB (30ມື້)",
    "name_en": "Internet 70GB (30days)",
    "desc_la": "ເບີເນັດ",
    "desc_en": "Net-Sim",
    "price": "150000",
    "code": "*131*568#",
    "prereq_la": "",
    "prereq_en": "",
    "category": "net-sim",
    "steps": ["Dial *131*568#", "Press call", "Wait for confirmation SMS"]
  },
  {
    "id": 21,
    "name_la": "95GB (30ມື້)",
    "name_en": "Internet 95GB (30days)",
    "desc_la": "ເບີເນັດ",
    "desc_en": "Net-Sim",
    "price": "200000",
    "code": "*131*569#",
    "prereq_la": "",
    "prereq_en": "",
    "category": "net-sim",
    "steps": ["Dial *131*569#", "Press call", "Wait for confirmation SMS"]
  }
]